{
  "prototype_name": "Student Chat AI",
  "theme": "Educational, friendly, modern, approachable for students - clean and engaging interface that feels safe and welcoming",
  "created_date": "2025",
  "target_audience": "Students from middle school to university level who want to practice communication skills",
  
  "color_palette": {
    "primary": {
      "hex": "#14b8a6",
      "tailwind": "teal-500",
      "usage": "Primary CTAs, active states, key interactive elements, chat send buttons"
    },
    "secondary": {
      "hex": "#3b82f6",
      "tailwind": "blue-500",
      "usage": "Secondary actions, links, info indicators, educational content highlights"
    },
    "accent": {
      "hex": "#8b5cf6",
      "tailwind": "violet-500",
      "usage": "Achievements, gamification elements, special features, AI responses"
    },
    "semantic": {
      "success": "#10b981",
      "warning": "#f59e0b",
      "error": "#ef4444",
      "info": "#3b82f6"
    },
    "neutrals": {
      "background": "#f9fafb",
      "surface": "#ffffff",
      "border": "#e5e7eb",
      "text_primary": "#111827",
      "text_secondary": "#6b7280",
      "text_tertiary": "#9ca3af"
    }
  },
  
  "typography": {
    "font_family": "Inter",
    "cdn_link": "https://fonts.googleapis.com/css2?family=Inter:wght@400;500;600;700&display=swap",
    "weights": {
      "regular": 400,
      "medium": 500,
      "semibold": 600,
      "bold": 700
    },
    "scale": {
      "xs": "0.75rem / 12px",
      "sm": "0.875rem / 14px",
      "base": "1rem / 16px",
      "lg": "1.125rem / 18px",
      "xl": "1.25rem / 20px",
      "2xl": "1.5rem / 24px",
      "3xl": "1.875rem / 30px",
      "4xl": "2.25rem / 36px",
      "5xl": "3rem / 48px",
      "6xl": "3.75rem / 60px"
    },
    "line_heights": {
      "tight": "1.25",
      "normal": "1.5",
      "relaxed": "1.75"
    }
  },
  
  "icon_system": {
    "library": "Lucide",
    "cdn_link": "https://unpkg.com/lucide@latest",
    "initialization": "lucide.createIcons()",
    "approach": "Inline SVG via data-lucide attributes for flexibility and easy styling",
    "size_default": "24",
    "stroke_width": "2",
    "color_usage": "Inherit from parent text color or use theme colors for semantic meaning",
    "common_icons": {
      "navigation": ["home", "menu", "x", "chevron-left", "chevron-right", "chevron-down"],
      "chat": ["message-circle", "message-square", "send", "mic", "smile", "paperclip", "image"],
      "user": ["user", "user-circle", "users", "user-plus", "user-check"],
      "actions": ["edit-3", "trash-2", "copy", "check", "x", "more-horizontal", "more-vertical"],
      "status": ["check-circle", "alert-circle", "info", "help-circle", "alert-triangle"],
      "learning": ["book-open", "graduation-cap", "award", "star", "bookmark", "lightbulb"],
      "interface": ["settings", "search", "filter", "clock", "calendar", "bell"],
      "communication": ["phone", "video", "volume-2", "volume-x", "headphones"]
    },
    "usage_example": "<i data-lucide=\"message-circle\" class=\"w-6 h-6 text-teal-500\"></i>",
    "sizing_guide": {
      "w-4 h-4": "16px - inline with text, small indicators",
      "w-5 h-5": "20px - buttons, navigation items",
      "w-6 h-6": "24px - standard UI icons (recommended default)",
      "w-8 h-8": "32px - feature icons, larger buttons",
      "w-12 h-12": "48px - profile avatars, hero icons"
    }
  },
  
  "imagery": {
    "usage_context": "web-app",
    "generation_guidelines": {
      "when_to_generate": [
        "Landing page hero backgrounds (if needed)",
        "Onboarding illustrations showing diverse students",
        "Tutorial/help section graphics",
        "Achievement badge backgrounds",
        "Empty state illustrations"
      ],
      "when_to_skip": [
        "Main chat interface - use icons and clean UI instead",
        "Navigation elements - icons are clearer",
        "Action buttons - rely on icons and text",
        "User profile areas - use avatar placeholders with initials",
        "Dashboard widgets - data visualizations and icons preferred"
      ],
      "style_preferences": [
        "Friendly illustration style with diverse student representation",
        "Clean, minimalist aesthetic that doesn't distract from learning",
        "Warm, welcoming color palette matching teal/blue/violet scheme",
        "Professional quality appropriate for educational context",
        "Inclusive and accessible visual language"
      ],
      "aspect_ratios": {
        "hero_background": "16:9 - wide format for landing pages",
        "feature_illustration": "1:1 or 4:3 - square or slightly wide",
        "empty_state": "1:1 - square illustrations",
        "achievement_badge": "1:1 - square format",
        "tutorial_graphic": "4:3 - slightly wide for explanatory content"
      }
    },
    "prompt_template": "[Subject: diverse students engaged in learning/chatting], clean modern illustration style, educational and friendly, teal #14b8a6 and blue #3b82f6 color palette, welcoming atmosphere, [aspect ratio], professional educational quality, inclusive representation",
    "file_path_convention": "student-chat-ai/images/[descriptive-name].png"
  },
  
  "spacing": {
    "system": "Tailwind default scale (4px base unit)",
    "container_max_width": "1280px (max-w-7xl) for main content, 896px (max-w-4xl) for chat interface",
    "section_vertical_padding": "py-12 md:py-16",
    "section_horizontal_padding": "px-4 sm:px-6 lg:px-8",
    "component_padding": {
      "button": "px-5 py-2.5",
      "card": "p-6",
      "input": "px-4 py-3",
      "chat_bubble": "px-4 py-2.5",
      "chat_container": "p-4 md:p-6"
    }
  },
  
  "effects": {
    "glassmorphism": {
      "css_class": "glass",
      "properties": {
        "background": "rgba(255, 255, 255, 0.9)",
        "backdrop_filter": "blur(12px) saturate(180%)",
        "border": "1px solid rgba(229, 231, 235, 0.8)"
      },
      "usage": "Chat message containers, sidebar panels, modal overlays, floating action elements"
    },
    "shadows": {
      "sm": "0 1px 2px 0 rgba(0, 0, 0, 0.05)",
      "base": "0 1px 3px 0 rgba(0, 0, 0, 0.1), 0 1px 2px 0 rgba(0, 0, 0, 0.06)",
      "md": "0 4px 6px -1px rgba(0, 0, 0, 0.1), 0 2px 4px -1px rgba(0, 0, 0, 0.06)",
      "lg": "0 10px 15px -3px rgba(0, 0, 0, 0.1), 0 4px 6px -2px rgba(0, 0, 0, 0.05)",
      "chat": "0 2px 8px 0 rgba(0, 0, 0, 0.08)"
    },
    "transitions": {
      "duration_fast": "150ms",
      "duration_base": "200ms",
      "duration_slow": "300ms",
      "easing": "cubic-bezier(0.4, 0, 0.2, 1)",
      "hover_scale": "1.01",
      "hover_scale_button": "1.02"
    },
    "gradients": {
      "background_primary": "bg-gradient-to-br from-gray-50 to-teal-50",
      "background_hero": "bg-gradient-to-br from-teal-50 via-blue-50 to-violet-50",
      "button_primary": "bg-gradient-to-r from-teal-500 to-teal-600",
      "accent": "bg-gradient-to-br from-violet-500 to-purple-600",
      "chat_user": "bg-gradient-to-br from-teal-500 to-teal-600",
      "chat_ai": "bg-gradient-to-br from-blue-500 to-violet-500"
    }
  },
  
  "components": {
    "buttons": {
      "primary": {
        "classes": "bg-teal-500 hover:bg-teal-600 text-white px-5 py-2.5 rounded-lg transition-all duration-200 transform hover:scale-102 shadow-md font-medium focus:outline-none focus:ring-2 focus:ring-teal-400 focus:ring-offset-2",
        "usage": "Primary CTAs, send message buttons, save actions, main interactive elements"
      },
      "secondary": {
        "classes": "bg-white hover:bg-gray-50 text-gray-700 px-5 py-2.5 rounded-lg transition-all duration-200 transform hover:scale-102 shadow-md border border-gray-300 font-medium focus:outline-none focus:ring-2 focus:ring-blue-400 focus:ring-offset-2",
        "usage": "Secondary actions, cancel buttons, alternative choices"
      },
      "text": {
        "classes": "text-teal-600 hover:text-teal-700 transition-colors duration-200 font-medium focus:outline-none focus:underline",
        "usage": "Tertiary actions, inline links, subtle interactions"
      },
      "icon": {
        "classes": "p-2 rounded-lg hover:bg-gray-100 transition-colors duration-200 text-gray-600 hover:text-teal-600 focus:outline-none focus:ring-2 focus:ring-teal-400",
        "usage": "Icon-only buttons, toolbar actions, compact interfaces"
      }
    },
    "cards": {
      "base": {
        "classes": "bg-white rounded-xl shadow-md p-6 border border-gray-200 transition-all duration-200",
        "usage": "Content containers, information panels, static displays"
      },
      "interactive": {
        "classes": "bg-white rounded-xl shadow-md p-6 border border-gray-200 hover:shadow-lg hover:-translate-y-0.5 transition-all duration-200 cursor-pointer",
        "usage": "Clickable cards, conversation starters, selectable options"
      },
      "chat_message": {
        "user": "bg-gradient-to-br from-teal-500 to-teal-600 text-white px-4 py-2.5 rounded-2xl rounded-tr-sm shadow-chat max-w-md ml-auto",
        "ai": "bg-white text-gray-800 px-4 py-2.5 rounded-2xl rounded-tl-sm shadow-chat max-w-md border border-gray-200"
      }
    },
    "navigation": {
      "container": "bg-white shadow-sm border-b border-gray-200 sticky top-0 z-50",
      "height": "h-16",
      "link": "text-gray-600 hover:text-teal-600 transition-colors duration-200 font-medium px-3 py-2 rounded-lg hover:bg-gray-50",
      "link_active": "text-teal-600 font-semibold bg-teal-50 px-3 py-2 rounded-lg"
    },
    "forms": {
      "input": "w-full px-4 py-3 rounded-lg border border-gray-300 focus:border-teal-500 focus:ring-2 focus:ring-teal-200 transition-all outline-none bg-white text-gray-900 placeholder-gray-400",
      "textarea": "w-full px-4 py-3 rounded-lg border border-gray-300 focus:border-teal-500 focus:ring-2 focus:ring-teal-200 transition-all outline-none bg-white text-gray-900 placeholder-gray-400 resize-none",
      "label": "block text-sm font-medium text-gray-700 mb-2",
      "error": "text-sm text-red-600 mt-1",
      "chat_input": "flex-1 px-4 py-3 rounded-full border border-gray-300 focus:border-teal-500 focus:ring-2 focus:ring-teal-200 transition-all outline-none bg-white text-gray-900 placeholder-gray-400"
    },
    "chat": {
      "sidebar": "w-64 bg-white border-r border-gray-200 p-4 space-y-2",
      "main_area": "flex-1 flex flex-col bg-gradient-to-br from-gray-50 to-teal-50",
      "message_list": "flex-1 overflow-y-auto p-4 space-y-4",
      "input_area": "border-t border-gray-200 bg-white p-4"
    }
  },
  
  "layout": {
    "responsive_breakpoints": {
      "sm": "640px - Large phones, phablets",
      "md": "768px - Tablets, small laptops",
      "lg": "1024px - Laptops, desktops",
      "xl": "1280px - Large desktops",
      "2xl": "1536px - Extra large screens"
    },
    "grid_patterns": {
      "2_column": "grid-cols-1 md:grid-cols-2 gap-6",
      "3_column": "grid-cols-1 md:grid-cols-2 lg:grid-cols-3 gap-6",
      "4_column": "grid-cols-1 sm:grid-cols-2 lg:grid-cols-4 gap-6",
      "chat_layout": "grid-cols-1 lg:grid-cols-[256px_1fr] gap-0"
    },
    "spacing_scale": {
      "section_gap": "gap-12 md:gap-16",
      "component_gap": "gap-6",
      "element_gap": "gap-4"
    }
  },
  
  "references_analyzed": [
    "https://discord.com",
    "https://www.khanacademy.org"
  ],
  
  "design_rationale": {
    "color_choices": "Teal (#14b8a6) chosen as primary for its educational, growth-oriented associations while remaining modern and friendly. Blue (#3b82f6) provides trust and calm - critical for learning environments. Violet (#8b5cf6) adds engaging, creative energy for AI interactions and gamification. This palette balances professional credibility (Khan Academy influence) with modern, engaging aesthetics (Discord influence).",
    
    "typography_choice": "Inter selected for exceptional readability across all sizes, crucial for students spending extended time reading chat messages. Its modern, friendly aesthetic strikes perfect balance between professional and approachable. Wide range of weights enables clear hierarchy in chat interfaces.",
    
    "icon_strategy": "Lucide provides comprehensive chat-focused icons (message bubbles, send, user profiles) with consistent stroke-based style. Perfect for web-app context where icons communicate actions quickly. Emphasis on communication, learning, and user management icons aligns with student chat AI functionality.",
    
    "imagery_approach": "Web-app focused prototype prioritizes clean UI with minimal imagery. Icons handle most visual communication. When images are needed (onboarding, empty states), they should feature diverse students in friendly illustration style, reinforcing safe and inclusive learning environment. No decorative images in main chat interface to maintain focus.",
    
    "effects_rationale": "Glassmorphism creates modern, lightweight feel for chat bubbles and panels - inspired by Discord's contemporary aesthetic but with educational restraint. Soft shadows provide depth without distraction. Rounded corners throughout (rounded-lg, rounded-xl, rounded-2xl) create approachable, friendly feeling essential for student comfort. Smooth transitions enhance polish without compromising performance."
  }
}